Metadata-Version: 2.1
Name: bartbroere_eland
Version: 8.17.1
Summary: [Development fork!] Python Client and Toolkit for DataFrames, Big Data, Machine Learning and ETL in Elasticsearch
Home-page: https://github.com/elastic/eland
Author: Steve Dodson
Author-email: steve.dodson@elastic.co
Maintainer: Elastic Client Library Maintainers
Maintainer-email: client-libs@elastic.co
License: Apache-2.0
Keywords: elastic eland pandas python
Classifier: Development Status :: 5 - Production/Stable
Classifier: License :: OSI Approved :: Apache Software License
Classifier: Environment :: Console
Classifier: Operating System :: OS Independent
Classifier: Intended Audience :: Developers
Classifier: Intended Audience :: Science/Research
Classifier: Operating System :: OS Independent
Classifier: Programming Language :: Python
Classifier: Programming Language :: Python :: 3
Classifier: Programming Language :: Python :: 3 :: Only
Classifier: Programming Language :: Python :: 3.9
Classifier: Programming Language :: Python :: 3.10
Classifier: Programming Language :: Python :: 3.11
Classifier: Programming Language :: Python :: 3.12
Classifier: Topic :: Scientific/Engineering
Requires-Python: >=3.9,<3.13
License-File: LICENSE.txt
License-File: NOTICE.txt
Requires-Dist: elasticsearch<9,>=8.3
Requires-Dist: pandas<3,>=1.5
Requires-Dist: matplotlib>=3.6
Requires-Dist: numpy<2,>=1.2.0
Requires-Dist: packaging
Requires-Dist: Click~=8.1.0
Requires-Dist: eql==0.9.19
Requires-Dist: jsl==0.2.4
Requires-Dist: jsonschema>=3.2.0
Requires-Dist: marko==2.0.1
Requires-Dist: marshmallow-dataclass[union]~=8.5.12
Requires-Dist: marshmallow-jsonschema~=0.12.0
Requires-Dist: marshmallow-union~=0.1.15
Requires-Dist: marshmallow~=3.13.0
Requires-Dist: pywin32; platform_system == "Windows"
Requires-Dist: pytoml==0.1.21
Requires-Dist: PyYAML~=5.3; python_version <= "3.9"
Requires-Dist: PyYAML~=6.0.1; python_version >= "3.10"
Requires-Dist: requests~=2.27
Requires-Dist: toml==0.10.0
Requires-Dist: typing-inspect==0.8.0
Requires-Dist: typing-extensions==4.5.0; python_version <= "3.11"
Requires-Dist: typing-extensions==4.8.0; python_version >= "3.12"
Requires-Dist: XlsxWriter~=1.3.6
Requires-Dist: semver==3.0.0-dev.4
Provides-Extra: xgboost
Requires-Dist: xgboost<2,>=0.90; extra == "xgboost"
Provides-Extra: scikit-learn
Requires-Dist: scikit-learn<1.4,>=1.3; extra == "scikit-learn"
Provides-Extra: lightgbm
Requires-Dist: lightgbm<4,>=2; extra == "lightgbm"
Provides-Extra: pytorch
Requires-Dist: requests<3; extra == "pytorch"
Requires-Dist: torch==2.3.1; extra == "pytorch"
Requires-Dist: tqdm; extra == "pytorch"
Requires-Dist: sentence-transformers<=2.7.0,>=2.1.0; extra == "pytorch"
Requires-Dist: transformers[sentencepiece]<4.44.0,>=4.31.0; extra == "pytorch"
Provides-Extra: all
Requires-Dist: tqdm; extra == "all"
Requires-Dist: lightgbm<4,>=2; extra == "all"
Requires-Dist: transformers[sentencepiece]<4.44.0,>=4.31.0; extra == "all"
Requires-Dist: sentence-transformers<=2.7.0,>=2.1.0; extra == "all"
Requires-Dist: xgboost<2,>=0.90; extra == "all"
Requires-Dist: torch==2.3.1; extra == "all"
Requires-Dist: requests<3; extra == "all"
Requires-Dist: scikit-learn<1.4,>=1.3; extra == "all"
